blq/__init__.py
blq/cli.py
blq/github.py
blq/query.py
blq/schema.sql
blq/serve.py
blq/commands/README.md
blq/commands/__init__.py
blq/commands/ci_cmd.py
blq/commands/core.py
blq/commands/events.py
blq/commands/execution.py
blq/commands/hooks_cmd.py
blq/commands/init_cmd.py
blq/commands/management.py
blq/commands/query_cmd.py
blq/commands/registry.py
blq/commands/report_cmd.py
blq/commands/serve_cmd.py
blq/commands/sync_cmd.py
blq/commands/watch_cmd.py
blq_cli-0.3.0.dist-info/METADATA
blq_cli-0.3.0.dist-info/WHEEL
blq_cli-0.3.0.dist-info/entry_points.txt
blq_cli-0.3.0.dist-info/RECORD
