Metadata-Version: 2.4
Name: blq-cli
Version: 0.3.0
Summary: Buidl Log Query - capture and query build/test logs with DuckDB
Project-URL: Homepage, https://blq-cli.readthedocs.com/
Project-URL: Repository, https://github.com/teaguesterling/blq-cli
Project-URL: Issues, https://github.com/teaguesterling/blq-cli/issues
Author-email: Teague Sterling <teaguesterling@gmail.com>
License-Expression: MIT
Keywords: build,ci,devops,duckdb,logs,test
Classifier: Development Status :: 3 - Alpha
Classifier: Environment :: Console
Classifier: Intended Audience :: Developers
Classifier: License :: OSI Approved :: MIT License
Classifier: Operating System :: OS Independent
Classifier: Programming Language :: Python :: 3
Classifier: Programming Language :: Python :: 3.10
Classifier: Programming Language :: Python :: 3.11
Classifier: Programming Language :: Python :: 3.12
Classifier: Topic :: Software Development :: Build Tools
Classifier: Topic :: Software Development :: Testing
Requires-Python: >=3.10
Requires-Dist: duckdb>=1.4.3
Requires-Dist: pandas>=2.0.0
Requires-Dist: pyyaml>=6.0
Requires-Dist: tabulate>=0.9.0
Requires-Dist: watchdog>=3.0.0
Provides-Extra: dev
Requires-Dist: mypy; extra == 'dev'
Requires-Dist: pytest-asyncio>=0.23.0; extra == 'dev'
Requires-Dist: pytest-cov; extra == 'dev'
Requires-Dist: pytest>=7.0; extra == 'dev'
Requires-Dist: ruff; extra == 'dev'
Provides-Extra: docs
Requires-Dist: mkdocs-material>=9.5.0; extra == 'docs'
Requires-Dist: mkdocs>=1.5.0; extra == 'docs'
Provides-Extra: mcp
Requires-Dist: fastmcp>=2.0.0; extra == 'mcp'
